bclib/__init__.py
bclib/edge.py
bclib/cache/__init__.py
bclib/cache/cache_status.py
bclib/cache/factory.py
bclib/cache/in_memory_cache_manager.py
bclib/cache/manager.py
bclib/cache/no_cache.py
bclib/cache/signal_base_cache_manager.py
bclib/cache/cache_item/__init__.py
bclib/cache/cache_item/base_cache_item.py
bclib/cache/cache_item/function_cache_item.py
bclib/cache/cache_item/scalar_cache_item.py
bclib/cache/signaler/__init__.py
bclib/cache/signaler/base_signaler.py
bclib/cache/signaler/factory.py
bclib/cache/signaler/no_signaler.py
bclib/cache/signaler/rabbit_signaler.py
bclib/cache/value_item/__init__.py
bclib/cache/value_item/array_value_item.py
bclib/cache/value_item/base_value_item.py
bclib/cache/value_item/scalar_value_item.py
bclib/context/__init__.py
bclib/context/client_source_context.py
bclib/context/client_source_member_context.py
bclib/context/context.py
bclib/context/json_base_request_context.py
bclib/context/merge_type.py
bclib/context/rabbit_context.py
bclib/context/request_context.py
bclib/context/restful_context.py
bclib/context/server_source_context.py
bclib/context/server_source_member_context.py
bclib/context/socket_context.py
bclib/context/source_context.py
bclib/context/source_member_context.py
bclib/context/web_context.py
bclib/context/websocket_context.py
bclib/db_manager/__init__.py
bclib/db_manager/db.py
bclib/db_manager/db_manager.py
bclib/db_manager/mongo_db.py
bclib/db_manager/odbc_db.py
bclib/db_manager/rabbit_connection.py
bclib/db_manager/restful_connection.py
bclib/db_manager/sql_db.py
bclib/db_manager/sqlite_db.py
bclib/dispatcher/__init__.py
bclib/dispatcher/callback_info.py
bclib/dispatcher/dev_server_dispatcher.py
bclib/dispatcher/dispatcher.py
bclib/dispatcher/dispatcher_helper.py
bclib/dispatcher/endpoint_dispatcher.py
bclib/dispatcher/idispatcher.py
bclib/dispatcher/routing_dispatcher.py
bclib/dispatcher/socket_dispatcher.py
bclib/dispatcher/websocket_session.py
bclib/dispatcher/websocket_session_manager.py
bclib-3.37.0.dist-info/licenses/LICENCE
bclib-3.37.0.dist-info/METADATA
bclib-3.37.0.dist-info/WHEEL
bclib-3.37.0.dist-info/top_level.txt
bclib-3.37.0.dist-info/RECORD
