Metadata-Version: 2.4
Name: bclib
Version: 3.37.0
Summary: Python base gateway for communicate with basiscore webserver
Home-page: https://github.com/Manzoomeh/BasisCore.Server.Edge/wiki
Author: Manzoomeh Negaran
Author-email: info@manzoomeh.ir
Project-URL: Bug Tracker, https://github.com/Manzoomeh/BasisCore.Server.Edge/issues
Classifier: Programming Language :: Python :: 3
Classifier: License :: OSI Approved :: MIT License
Classifier: Operating System :: OS Independent
Requires-Python: >=3.13
License-File: LICENCE
Requires-Dist: pika
Requires-Dist: requests
Requires-Dist: pymongo
Requires-Dist: pyodbc
Dynamic: author
Dynamic: author-email
Dynamic: classifier
Dynamic: description
Dynamic: description-content-type
Dynamic: home-page
Dynamic: license-file
Dynamic: project-url
Dynamic: requires-dist
Dynamic: requires-python
Dynamic: summary
